datastructures/linear/CDLL.py
datastructures/linear/CSLL.py
datastructures/linear/DLL.py
datastructures/linear/QueueLL.py
datastructures/linear/SLL.py
datastructures/linear/StackLL.py
datastructures/linear/__init__.py
datastructures/nodes/DNode.py
datastructures/nodes/SNode.py
datastructures/nodes/TNode.py
datastructures/nodes/__init__.py
datastructures/trees/AVL.py
datastructures/trees/BST.py
datastructures/trees/__init__.py
DataStructuresLiamTheodore-1.0.4.dist-info/METADATA
DataStructuresLiamTheodore-1.0.4.dist-info/WHEEL
DataStructuresLiamTheodore-1.0.4.dist-info/top_level.txt
DataStructuresLiamTheodore-1.0.4.dist-info/RECORD
