Metadata-Version: 2.1
Name: DataStructuresLiamTheodore
Version: 1.0.4
Summary: Datastructures library for ENSF 338 Final Project.
Author: Theodore and Liam
Author-email: liam.mah@ucalgary.ca
License: UNKNOWN
Platform: UNKNOWN
